planestress/__init__.py
planestress/__main__.py
planestress/analysis/__init__.py
planestress/analysis/finite_element.py
planestress/analysis/plane_stress.py
planestress/analysis/solver.py
planestress/analysis/utils.py
planestress/post/__init__.py
planestress/post/plotting.py
planestress/post/results.py
planestress/pre/__init__.py
planestress/pre/boundary_condition.py
planestress/pre/geometry.py
planestress/pre/library.py
planestress/pre/load_case.py
planestress/pre/material.py
planestress/pre/mesh.py
planestress/py.typed
planestress-0.0.4.dist-info/LICENSE
planestress-0.0.4.dist-info/METADATA
planestress-0.0.4.dist-info/WHEEL
planestress-0.0.4.dist-info/entry_points.txt
planestress-0.0.4.dist-info/RECORD
